.gitignore
license.txt
readme.md
setup.cfg
setup.py
textreader/__init__.py
textreader/__init__.pyc
textreader/coefs.py
textreader/reader.py
textreader.egg-info/PKG-INFO
textreader.egg-info/SOURCES.txt
textreader.egg-info/dependency_links.txt
textreader.egg-info/requires.txt
textreader.egg-info/top_level.txt
textreader/data/AoAKuperman.csv
textreader/data/SUBTLEXus.csv
textreader/data/__init__.py
textreader/data/en_core_web_sm-3.0.0.tar.gz
textreader/data/en_core_web_sm-3.0.0/accuracy.json
textreader/data/en_core_web_sm-3.0.0/config.cfg
textreader/data/en_core_web_sm-3.0.0/meta.json
textreader/data/en_core_web_sm-3.0.0/tokenizer
textreader/data/en_core_web_sm-3.0.0/attribute_ruler/patterns
textreader/data/en_core_web_sm-3.0.0/lemmatizer/lookups/lookups.bin
textreader/data/en_core_web_sm-3.0.0/ner/cfg
textreader/data/en_core_web_sm-3.0.0/ner/model
textreader/data/en_core_web_sm-3.0.0/ner/moves
textreader/data/en_core_web_sm-3.0.0/parser/cfg
textreader/data/en_core_web_sm-3.0.0/parser/model
textreader/data/en_core_web_sm-3.0.0/parser/moves
textreader/data/en_core_web_sm-3.0.0/senter/cfg
textreader/data/en_core_web_sm-3.0.0/senter/model
textreader/data/en_core_web_sm-3.0.0/tagger/cfg
textreader/data/en_core_web_sm-3.0.0/tagger/model
textreader/data/en_core_web_sm-3.0.0/tok2vec/cfg
textreader/data/en_core_web_sm-3.0.0/tok2vec/model
textreader/data/en_core_web_sm-3.0.0/vocab/key2row
textreader/data/en_core_web_sm-3.0.0/vocab/lookups.bin
textreader/data/en_core_web_sm-3.0.0/vocab/strings.json
textreader/data/en_core_web_sm-3.0.0/vocab/vectors